{
  "project_info": {
    "project_number": "745747420526",
    "project_id": "estholon-values-app",
    "storage_bucket": "estholon-values-app.appspot.com"
  },
  "client": [
    {
      "client_info": {
        "mobilesdk_app_id": "1:745747420526:android:a8d3bbaf0fa0d1adebdd7f",
        "android_client_info": {
          "package_name": "com.estholon.estholonvalues"
        }
      },
      "oauth_client": [
        {
          "client_id": "745747420526-dqt8ctl1tvks36u09rcevekjrrm0emuf.apps.googleusercontent.com",
          "client_type": 1,
          "android_info": {
            "package_name": "com.estholon.estholonvalues",
            "certificate_hash": "afd0b80fbdb6d72c4c7bc94febcbeedf1ed1e0a1"
          }
        },
        {
          "client_id": "745747420526-2psu4u2dbgl976kp52fckoem5t26aujb.apps.googleusercontent.com",
          "client_type": 3
        }
      ],
      "api_key": [
        {
          "current_key": "AIzaSyA5HsJ-1kdoulxp5ozIaqx3y-eSh7lKNxo"
        }
      ],
      "services": {
        "appinvite_service": {
          "other_platform_oauth_client": [
            {
              "client_id": "745747420526-2psu4u2dbgl976kp52fckoem5t26aujb.apps.googleusercontent.com",
              "client_type": 3
            }
          ]
        }
      }
    },
    {
      "client_info": {
        "mobilesdk_app_id": "1:745747420526:android:a7607e7bff2170b1ebdd7f",
        "android_client_info": {
          "package_name": "com.estholon.estholonvalues.debug"
        }
      },
      "oauth_client": [
        {
          "client_id": "745747420526-00j43bc339t31t3hfkbfigivagalvp5v.apps.googleusercontent.com",
          "client_type": 1,
          "android_info": {
            "package_name": "com.estholon.estholonvalues.debug",
            "certificate_hash": "015d7c0658927641e0cede93b7246d3da6e4d5c2"
          }
        },
        {
          "client_id": "745747420526-2psu4u2dbgl976kp52fckoem5t26aujb.apps.googleusercontent.com",
          "client_type": 3
        }
      ],
      "api_key": [
        {
          "current_key": "AIzaSyA5HsJ-1kdoulxp5ozIaqx3y-eSh7lKNxo"
        }
      ],
      "services": {
        "appinvite_service": {
          "other_platform_oauth_client": [
            {
              "client_id": "745747420526-2psu4u2dbgl976kp52fckoem5t26aujb.apps.googleusercontent.com",
              "client_type": 3
            }
          ]
        }
      }
    }
  ],
  "configuration_version": "1"
}